neurve/__init__.py
neurve/distance.py
neurve/mmd.py
neurve/samplers.py
neurve/contrastive/__init__.py
neurve/contrastive/dataset.py
neurve/contrastive/loss.py
neurve/contrastive/models.py
neurve/contrastive/trainer.py
neurve/contrastive/utils.py
neurve/core/__init__.py
neurve/core/models.py
neurve/core/trainer.py
neurve/metric_learning/__init__.py
neurve/metric_learning/loss.py
neurve/metric_learning/metrics.py
neurve/metric_learning/models.py
neurve/metric_learning/trainer.py
neurve-0.1.0.dist-info/LICENSE
neurve-0.1.0.dist-info/METADATA
neurve-0.1.0.dist-info/WHEEL
neurve-0.1.0.dist-info/top_level.txt
neurve-0.1.0.dist-info/RECORD
