Metadata-Version: 2.1
Name: neurve
Version: 0.1.0
Summary: atlas learning
Requires-Python: >=3.8
License-File: LICENSE
Requires-Dist: numpy >=1.17.4
Requires-Dist: torch >=1.3.1
Requires-Dist: torchvision >=0.4.2
Requires-Dist: scipy >=1.5.3
Requires-Dist: tqdm
Requires-Dist: tensorboardX
Provides-Extra: dev
Requires-Dist: setuptools-scm ; extra == 'dev'
Requires-Dist: pre-commit ; extra == 'dev'
Provides-Extra: test
Requires-Dist: pytest ; extra == 'test'
Provides-Extra: wandb
Requires-Dist: wandb ; extra == 'wandb'
